{
     "0": {"file": "Wav/TONE.wav", "pitch_shift": -60.0},
     "1": {"file": "Wav/TONE.wav", "pitch_shift": -59.0},
     "2": {"file": "Wav/TONE.wav", "pitch_shift": -58.0},
     "3": {"file": "Wav/TONE.wav", "pitch_shift": -57.0},
     "4": {"file": "Wav/TONE.wav", "pitch_shift": -56.0},
     "5": {"file": "Wav/TONE.wav", "pitch_shift": -55.0},
     "6": {"file": "Wav/TONE.wav", "pitch_shift": -54.0},
     "7": {"file": "Wav/TONE.wav", "pitch_shift": -53.0},
     "8": {"file": "Wav/TONE.wav", "pitch_shift": -52.0},
     "9": {"file": "Wav/TONE.wav", "pitch_shift": -51.0},
    "10": {"file": "Wav/TONE.wav", "pitch_shift": -50.0},
    "11": {"file": "Wav/TONE.wav", "pitch_shift": -49.0},
    "12": {"file": "Wav/TONE.wav", "pitch_shift": -48.0},
    "13": {"file": "Wav/TONE.wav", "pitch_shift": -47.0},
    "14": {"file": "Wav/TONE.wav", "pitch_shift": -46.0},
    "15": {"file": "Wav/TONE.wav", "pitch_shift": -45.0},
    "16": {"file": "Wav/TONE.wav", "pitch_shift": -44.0},
    "17": {"file": "Wav/TONE.wav", "pitch_shift": -43.0},
    "18": {"file": "Wav/TONE.wav", "pitch_shift": -42.0},
    "19": {"file": "Wav/TONE.wav", "pitch_shift": -41.0},
    "20": {"file": "Wav/TONE.wav", "pitch_shift": -40.0},
    "21": {"file": "Wav/TONE.wav", "pitch_shift": -39.0},
    "22": {"file": "Wav/TONE.wav", "pitch_shift": -38.0},
    "23": {"file": "Wav/TONE.wav", "pitch_shift": -37.0},
    "24": {"file": "Wav/TONE.wav", "pitch_shift": -36.0},
    "25": {"file": "Wav/TONE.wav", "pitch_shift": -35.0},
    "26": {"file": "Wav/TONE.wav", "pitch_shift": -34.0},
    "27": {"file": "Wav/TONE.wav", "pitch_shift": -33.0},
    "28": {"file": "Wav/TONE.wav", "pitch_shift": -32.0},
    "29": {"file": "Wav/TONE.wav", "pitch_shift": -31.0},
    "30": {"file": "Wav/TONE.wav", "pitch_shift": -30.0},
    "31": {"file": "Wav/TONE.wav", "pitch_shift": -29.0},
    "32": {"file": "Wav/TONE.wav", "pitch_shift": -28.0},
    "33": {"file": "Wav/TONE.wav", "pitch_shift": -27.0},
    "34": {"file": "Wav/TONE.wav", "pitch_shift": -26.0},
    "35": {"file": "Wav/TONE.wav", "pitch_shift": -25.0},
    "36": {"file": "Wav/TONE.wav", "pitch_shift": -24.0},
    "37": {"file": "Wav/TONE.wav", "pitch_shift": -23.0},
    "38": {"file": "Wav/TONE.wav", "pitch_shift": -22.0},
    "39": {"file": "Wav/TONE.wav", "pitch_shift": -21.0},
    "40": {"file": "Wav/TONE.wav", "pitch_shift": -20.0},
    "41": {"file": "Wav/TONE.wav", "pitch_shift": -19.0},
    "42": {"file": "Wav/TONE.wav", "pitch_shift": -18.0},
    "43": {"file": "Wav/TONE.wav", "pitch_shift": -17.0},
    "44": {"file": "Wav/TONE.wav", "pitch_shift": -16.0},
    "45": {"file": "Wav/TONE.wav", "pitch_shift": -15.0},
    "46": {"file": "Wav/TONE.wav", "pitch_shift": -14.0},
    "47": {"file": "Wav/TONE.wav", "pitch_shift": -13.0},
    "48": {"file": "Wav/TONE.wav", "pitch_shift": -12.0},
    "49": {"file": "Wav/TONE.wav", "pitch_shift": -11.0},
    "50": {"file": "Wav/TONE.wav", "pitch_shift": -10.0},
    "51": {"file": "Wav/TONE.wav", "pitch_shift": -9.0},
    "52": {"file": "Wav/TONE.wav", "pitch_shift": -8.0},
    "53": {"file": "Wav/TONE.wav", "pitch_shift": -7.0},
    "54": {"file": "Wav/TONE.wav", "pitch_shift": -6.0},
    "55": {"file": "Wav/TONE.wav", "pitch_shift": -5.0},
    "56": {"file": "Wav/TONE.wav", "pitch_shift": -4.0},
    "57": {"file": "Wav/TONE.wav", "pitch_shift": -3.0},
    "58": {"file": "Wav/TONE.wav", "pitch_shift": -2.0},
    "59": {"file": "Wav/TONE.wav", "pitch_shift": -1.0},
    "60": {"file": "Wav/TONE.wav", "pitch_shift": 0.0}
    "61": {"file": "Wav/TONE.wav", "pitch_shift": 1.0},
    "62": {"file": "Wav/TONE.wav", "pitch_shift": 2.0},
    "63": {"file": "Wav/TONE.wav", "pitch_shift": 3.0},
    "64": {"file": "Wav/TONE.wav", "pitch_shift": 4.0},
    "65": {"file": "Wav/TONE.wav", "pitch_shift": 5.0},
    "66": {"file": "Wav/TONE.wav", "pitch_shift": 6.0},
    "67": {"file": "Wav/TONE.wav", "pitch_shift": 7.0},
    "68": {"file": "Wav/TONE.wav", "pitch_shift": 8.0},
    "69": {"file": "Wav/TONE.wav", "pitch_shift": 9.0},
    "70": {"file": "Wav/TONE.wav", "pitch_shift": 10.0},
    "71": {"file": "Wav/TONE.wav", "pitch_shift": 11.0},
    "72": {"file": "Wav/TONE.wav", "pitch_shift": 12.0},
    "73": {"file": "Wav/TONE.wav", "pitch_shift": 13.0},
    "74": {"file": "Wav/TONE.wav", "pitch_shift": 14.0},
    "75": {"file": "Wav/TONE.wav", "pitch_shift": 15.0},
    "76": {"file": "Wav/TONE.wav", "pitch_shift": 16.0},
    "77": {"file": "Wav/TONE.wav", "pitch_shift": 17.0},
    "78": {"file": "Wav/TONE.wav", "pitch_shift": 18.0},
    "79": {"file": "Wav/TONE.wav", "pitch_shift": 19.0},
    "80": {"file": "Wav/TONE.wav", "pitch_shift": 20.0},
    "81": {"file": "Wav/TONE.wav", "pitch_shift": 21.0},
    "82": {"file": "Wav/TONE.wav", "pitch_shift": 22.0},
    "83": {"file": "Wav/TONE.wav", "pitch_shift": 23.0},
    "84": {"file": "Wav/TONE.wav", "pitch_shift": 24.0},
    "85": {"file": "Wav/TONE.wav", "pitch_shift": 25.0},
    "86": {"file": "Wav/TONE.wav", "pitch_shift": 26.0},
    "87": {"file": "Wav/TONE.wav", "pitch_shift": 27.0},
    "88": {"file": "Wav/TONE.wav", "pitch_shift": 28.0},
    "89": {"file": "Wav/TONE.wav", "pitch_shift": 29.0},
    "90": {"file": "Wav/TONE.wav", "pitch_shift": 30.0},
    "91": {"file": "Wav/TONE.wav", "pitch_shift": 31.0},
    "92": {"file": "Wav/TONE.wav", "pitch_shift": 32.0},
    "93": {"file": "Wav/TONE.wav", "pitch_shift": 33.0},
    "94": {"file": "Wav/TONE.wav", "pitch_shift": 34.0},
    "95": {"file": "Wav/TONE.wav", "pitch_shift": 35.0},
    "96": {"file": "Wav/TONE.wav", "pitch_shift": 36.0},
    "97": {"file": "Wav/TONE.wav", "pitch_shift": 37.0},
    "98": {"file": "Wav/TONE.wav", "pitch_shift": 38.0},
    "99": {"file": "Wav/TONE.wav", "pitch_shift": 39.0},
   "100": {"file": "Wav/TONE.wav", "pitch_shift": 40.0},
   "101": {"file": "Wav/TONE.wav", "pitch_shift": 41.0},
   "102": {"file": "Wav/TONE.wav", "pitch_shift": 42.0},
   "103": {"file": "Wav/TONE.wav", "pitch_shift": 43.0},
   "104": {"file": "Wav/TONE.wav", "pitch_shift": 44.0},
   "105": {"file": "Wav/TONE.wav", "pitch_shift": 45.0},
   "106": {"file": "Wav/TONE.wav", "pitch_shift": 46.0},
   "107": {"file": "Wav/TONE.wav", "pitch_shift": 47.0},
   "108": {"file": "Wav/TONE.wav", "pitch_shift": 48.0},
   "109": {"file": "Wav/TONE.wav", "pitch_shift": 49.0},
   "110": {"file": "Wav/TONE.wav", "pitch_shift": 50.0},
   "111": {"file": "Wav/TONE.wav", "pitch_shift": 51.0},
   "112": {"file": "Wav/TONE.wav", "pitch_shift": 52.0},
   "113": {"file": "Wav/TONE.wav", "pitch_shift": 53.0},
   "114": {"file": "Wav/TONE.wav", "pitch_shift": 54.0},
   "115": {"file": "Wav/TONE.wav", "pitch_shift": 55.0},
   "116": {"file": "Wav/TONE.wav", "pitch_shift": 56.0},
   "117": {"file": "Wav/TONE.wav", "pitch_shift": 57.0},
   "118": {"file": "Wav/TONE.wav", "pitch_shift": 58.0},
   "119": {"file": "Wav/TONE.wav", "pitch_shift": 59.0},
   "120": {"file": "Wav/TONE.wav", "pitch_shift": 60.0},
   "121": {"file": "Wav/TONE.wav", "pitch_shift": 61.0},
   "122": {"file": "Wav/TONE.wav", "pitch_shift": 62.0},
   "123": {"file": "Wav/TONE.wav", "pitch_shift": 63.0},
   "124": {"file": "", "pitch_shift": 0.0},
   "125": {"file": "", "pitch_shift": 0.0},
   "126": {"file": "", "pitch_shift": 0.0},
   "127": {"file": "", "pitch_shift": 0.0}
}
